byted_overpass_caijing_bytepay_bizfund_flowmanager/__init__.py
byted_overpass_caijing_bytepay_bizfund_flowmanager-0.0.1.dist-info/METADATA
byted_overpass_caijing_bytepay_bizfund_flowmanager-0.0.1.dist-info/WHEEL
byted_overpass_caijing_bytepay_bizfund_flowmanager-0.0.1.dist-info/top_level.txt
byted_overpass_caijing_bytepay_bizfund_flowmanager-0.0.1.dist-info/RECORD
